simpleusers/__init__.py
simpleusers/users.py
simpleusers-0.0.8.dist-info/METADATA
simpleusers-0.0.8.dist-info/WHEEL
simpleusers-0.0.8.dist-info/licenses/LICENSE
simpleusers-0.0.8.dist-info/RECORD
