Metadata-Version: 2.1
Name: simpleusers
Version: 0.0.8
Summary: A small user db library
Project-URL: Homepage, https://github.com/SomethingGeneric/simpleusers
Project-URL: Bug Tracker, https://github.com/SomethingGeneric/simpleusers/issues
Author-email: Matt C <matt@xhec.dev>
License: MIT License
License-File: LICENSE
Classifier: License :: OSI Approved :: MIT License
Classifier: Operating System :: OS Independent
Classifier: Programming Language :: Python :: 3
Requires-Python: >=3.7
Requires-Dist: passlib
Requires-Dist: pyyaml
